django_wysiwyg_redactor-0.5.1.dist-info/DESCRIPTION.rst
django_wysiwyg_redactor-0.5.1.dist-info/METADATA
django_wysiwyg_redactor-0.5.1.dist-info/RECORD
django_wysiwyg_redactor-0.5.1.dist-info/WHEEL
django_wysiwyg_redactor-0.5.1.dist-info/metadata.json
django_wysiwyg_redactor-0.5.1.dist-info/top_level.txt
redactor/.DS_Store
redactor/__init__.py
redactor/fields.py
redactor/forms.py
redactor/handlers.py
redactor/urls.py
redactor/utils.py
redactor/views.py
redactor/widgets.py
redactor/static/.DS_Store
redactor/static/redactor/django_admin.css
redactor/static/redactor/jquery.redactor.init.js
redactor/static/redactor/redactor.css
redactor/static/redactor/redactor.js
redactor/static/redactor/redactor.min.css
redactor/static/redactor/redactor.min.js
redactor/static/redactor/_scss/_content.scss
redactor/static/redactor/_scss/_dropdown.scss
redactor/static/redactor/_scss/_icons.scss
redactor/static/redactor/_scss/_mixins.scss
redactor/static/redactor/_scss/_modal.scss
redactor/static/redactor/_scss/_ui.scss
redactor/static/redactor/_scss/_variables.scss
redactor/static/redactor/_scss/redactor.scss
redactor/static/redactor/langs/ar.js
redactor/static/redactor/langs/de.js
redactor/static/redactor/langs/en.js
redactor/static/redactor/langs/es.js
redactor/static/redactor/langs/fa.js
redactor/static/redactor/langs/fi.js
redactor/static/redactor/langs/fr.js
redactor/static/redactor/langs/he.js
redactor/static/redactor/langs/hu.js
redactor/static/redactor/langs/it.js
redactor/static/redactor/langs/ja.js
redactor/static/redactor/langs/ko.js
redactor/static/redactor/langs/nl.js
redactor/static/redactor/langs/pl.js
redactor/static/redactor/langs/pt_br.js
redactor/static/redactor/langs/ru.js
redactor/static/redactor/langs/sv.js
redactor/static/redactor/langs/tr.js
redactor/static/redactor/langs/ua.js
redactor/static/redactor/langs/zh_cn.js
redactor/static/redactor/langs/zh_tw.js
