Metadata-Version: 2.0
Name: django-wysiwyg-redactor
Version: 0.5.1
Summary: django-wysiwyg-redactor is a lightweight responsive wysiwyg editor for Django
Home-page: https://github.com/douglasmiranda/django-wysiwyg-redactor
Author: Douglas Miranda
Author-email: douglasmirandasilva@gmail.com
License: MIT
Keywords: django,admin,wysiwyg,editor,redactor,redactorjs
Platform: UNKNOWN
Classifier: Development Status :: 5 - Production/Stable
Classifier: Environment :: Web Environment
Classifier: Framework :: Django
Classifier: Intended Audience :: Developers
Classifier: License :: OSI Approved :: BSD License
Classifier: Operating System :: OS Independent
Classifier: Programming Language :: Python
Classifier: Programming Language :: Python :: 3
Requires-Dist: setuptools
